LICENCE.txt
MANIFEST.in
README.rst
pyproject.toml
setup.cfg
setup.py
crispy_forms_foundation/__init__.py
crispy_forms_foundation/forms.py
crispy_forms_foundation/models.py
crispy_forms_foundation/settings.py
crispy_forms_foundation.egg-info/PKG-INFO
crispy_forms_foundation.egg-info/SOURCES.txt
crispy_forms_foundation.egg-info/dependency_links.txt
crispy_forms_foundation.egg-info/requires.txt
crispy_forms_foundation.egg-info/top_level.txt
crispy_forms_foundation.egg-info/zip-safe
crispy_forms_foundation/layout/__init__.py
crispy_forms_foundation/layout/base.py
crispy_forms_foundation/layout/buttons.py
crispy_forms_foundation/layout/containers.py
crispy_forms_foundation/layout/fields.py
crispy_forms_foundation/layout/grid.py
crispy_forms_foundation/locale/de/LC_MESSAGES/django.mo
crispy_forms_foundation/locale/de/LC_MESSAGES/django.po
crispy_forms_foundation/locale/fr/LC_MESSAGES/django.mo
crispy_forms_foundation/locale/fr/LC_MESSAGES/django.po
crispy_forms_foundation/static/js/crispy_forms_foundation/plugins.js
crispy_forms_foundation/templates/foundation-6/betterform.html
crispy_forms_foundation/templates/foundation-6/display_form.html
crispy_forms_foundation/templates/foundation-6/errors.html
crispy_forms_foundation/templates/foundation-6/errors_formset.html
crispy_forms_foundation/templates/foundation-6/field.html
crispy_forms_foundation/templates/foundation-6/field.strict.html
crispy_forms_foundation/templates/foundation-6/inline_switch.html
crispy_forms_foundation/templates/foundation-6/multifield.html
crispy_forms_foundation/templates/foundation-6/switch.html
crispy_forms_foundation/templates/foundation-6/uni_form.html
crispy_forms_foundation/templates/foundation-6/uni_formset.html
crispy_forms_foundation/templates/foundation-6/whole_uni_form.html
crispy_forms_foundation/templates/foundation-6/whole_uni_formset.html
crispy_forms_foundation/templates/foundation-6/layout/accordion-holder.html
crispy_forms_foundation/templates/foundation-6/layout/accordion-item.html
crispy_forms_foundation/templates/foundation-6/layout/basebutton.html
crispy_forms_foundation/templates/foundation-6/layout/baseinput.html
crispy_forms_foundation/templates/foundation-6/layout/buttongroup.html
